gemini_txt_analyser/gemini_txt_analyser.py
gemini_txt_analyser-1.dist-info/LICENSE
gemini_txt_analyser-1.dist-info/METADATA
gemini_txt_analyser-1.dist-info/WHEEL
gemini_txt_analyser-1.dist-info/entry_points.txt
gemini_txt_analyser-1.dist-info/top_level.txt
gemini_txt_analyser-1.dist-info/RECORD
